sisifo/__init__.py
sisifo/_version.py
sisifo/abstract_task.py
sisifo/concrete_tasks.py
sisifo/data_collection.py
sisifo/named_collection.py
sisifo/plugins.py
sisifo/task_factory.py
sisifo/task_registry.py
sisifo/utils.py
sisifo_common/__init__.py
sisifo_common/parallel_pipeline.py
sisifo_common/pipeline.py
sisifo_common/run_script.py
sisifo-0.1.1.dist-info/WHEEL
sisifo-0.1.1.dist-info/METADATA
sisifo-0.1.1.dist-info/RECORD
