Metadata-Version: 2.1
Name: sisifo
Version: 0.1.1
Summary: Generic framework for running data pipelines
Home-page: https://github.com/guiferviz/sisifo
License: MIT
Keywords: tasks,framework,pipeline
Author: guiferviz
Author-email: guiferviz@gmail.com
Requires-Python: >=3.7,<4.0
Classifier: License :: OSI Approved :: MIT License
Classifier: Programming Language :: Python :: 3
Classifier: Programming Language :: Python :: 3.7
Classifier: Programming Language :: Python :: 3.8
Classifier: Programming Language :: Python :: 3.9
Classifier: Topic :: Software Development :: Libraries :: Python Modules
Project-URL: Repository, https://github.com/guiferviz/sisifo
